[
  {
    "avg_tracks": 20.931034088134766,
    "conflicting_visit_pairs": 5915,
    "conflicts": 33,
    "delay_cost_type": "Continuous",
    "index": 0,
    "name": "origA1",
    "solves": [
      {
        "algorithm_time": 0.020809198,
        "avg_time_points": 1.4698310539018504,
        "cost": 6966,
        "delay_cost_type": "Continuous",
        "iterations": 90,
        "lb": 6966,
        "max_time_points": 9,
        "num_conflicts": 42,
        "num_time_points": 1827,
        "num_traveltime": 482,
        "objective_iters": 90,
        "resource_iters": 1,
        "sol_time": 38.222024,
        "solver_name": "SatDddSclTotalizer",
        "solver_time": 0.015825377,
        "status": "ok",
        "total_time": 0.036633683,
        "travel_and_resource_iters": 25,
        "travel_iters": 51,
        "ub": 6966
      }
    ],
    "trains": 29
  },
  {
    "avg_tracks": 18.176469802856445,
    "conflicting_visit_pairs": 1632,
    "conflicts": 33,
    "delay_cost_type": "Continuous",
    "index": 1,
    "name": "origA10",
    "solves": [
      {
        "algorithm_time": 1.8363703610000002,
        "avg_time_points": 2.9244094488188974,
        "cost": 7914,
        "delay_cost_type": "Continuous",
        "iterations": 125,
        "lb": 7914,
        "max_time_points": 11,
        "num_conflicts": 124,
        "num_time_points": 1857,
        "num_traveltime": 1012,
        "objective_iters": 125,
        "resource_iters": 1,
        "sol_time": 2698.581998,
        "solver_name": "SatDddSclTotalizer",
        "solver_time": 0.843957062,
        "status": "ok",
        "total_time": 2.680326537,
        "travel_and_resource_iters": 49,
        "travel_iters": 70,
        "ub": 7914
      }
    ],
    "trains": 17
  },
  {
    "avg_tracks": 19.83333396911621,
    "conflicting_visit_pairs": 6162,
    "conflicts": 33,
    "delay_cost_type": "Continuous",
    "index": 2,
    "name": "origA11",
    "solves": [
      {
        "algorithm_time": 0.629229882,
        "avg_time_points": 1.8852459016393444,
        "cost": 5209,
        "delay_cost_type": "Continuous",
        "iterations": 72,
        "lb": 5209,
        "max_time_points": 13,
        "num_conflicts": 115,
        "num_time_points": 2300,
        "num_traveltime": 842,
        "objective_iters": 72,
        "resource_iters": 1,
        "sol_time": 3967.973229,
        "solver_name": "SatDddSclTotalizer",
        "solver_time": 0.009577881,
        "status": "ok",
        "total_time": 0.638806275,
        "travel_and_resource_iters": 41,
        "travel_iters": 18,
        "ub": 5209
      }
    ],
    "trains": 30
  },
  {
    "avg_tracks": 21.714284896850586,
    "conflicting_visit_pairs": 6393,
    "conflicts": 33,
    "delay_cost_type": "Continuous",
    "index": 3,
    "name": "origA12",
    "solves": [
      {
        "algorithm_time": 1.3466741629999999,
        "avg_time_points": 2.0956591639871385,
        "cost": 9486,
        "delay_cost_type": "Continuous",
        "iterations": 91,
        "lb": 9486,
        "max_time_points": 15,
        "num_conflicts": 167,
        "num_time_points": 2607,
        "num_traveltime": 1045,
        "objective_iters": 91,
        "resource_iters": 1,
        "sol_time": 2264.033736,
        "solver_name": "SatDddSclTotalizer",
        "solver_time": 0.898672644,
        "status": "ok",
        "total_time": 2.245345729,
        "travel_and_resource_iters": 55,
        "travel_iters": 22,
        "ub": 9486
      }
    ],
    "trains": 28
  },
  {
    "avg_tracks": 19.0,
    "conflicting_visit_pairs": 3735,
    "conflicts": 33,
    "delay_cost_type": "Continuous",
    "index": 4,
    "name": "origA2",
    "solves": [
      {
        "algorithm_time": 0.7300841459999999,
        "avg_time_points": 2.4594871794871795,
        "cost": 8246,
        "delay_cost_type": "Continuous",
        "iterations": 112,
        "lb": 8246,
        "max_time_points": 18,
        "num_conflicts": 179,
        "num_time_points": 2398,
        "num_traveltime": 1108,
        "objective_iters": 112,
        "resource_iters": 1,
        "sol_time": 1316.118932,
        "solver_name": "SatDddSclTotalizer",
        "solver_time": 0.568458475,
        "status": "ok",
        "total_time": 1.298541494,
        "travel_and_resource_iters": 62,
        "travel_iters": 37,
        "ub": 8246
      }
    ],
    "trains": 25
  },
  {
    "avg_tracks": 22.375,
    "conflicting_visit_pairs": 2061,
    "conflicts": 33,
    "delay_cost_type": "Continuous",
    "index": 5,
    "name": "origA3",
    "solves": [
      {
        "algorithm_time": 0.016841231999999998,
        "avg_time_points": 1.6229508196721312,
        "cost": 2346,
        "delay_cost_type": "Continuous",
        "iterations": 59,
        "lb": 2346,
        "max_time_points": 7,
        "num_conflicts": 34,
        "num_time_points": 1188,
        "num_traveltime": 378,
        "objective_iters": 59,
        "resource_iters": 1,
        "sol_time": 22.7321,
        "solver_name": "SatDddSclTotalizer",
        "solver_time": 0.005291835,
        "status": "ok",
        "total_time": 0.022132275,
        "travel_and_resource_iters": 19,
        "travel_iters": 28,
        "ub": 2346
      }
    ],
    "trains": 16
  },
  {
    "avg_tracks": 19.214284896850586,
    "conflicting_visit_pairs": 1175,
    "conflicts": 33,
    "delay_cost_type": "Continuous",
    "index": 6,
    "name": "origA4",
    "solves": [
      {
        "algorithm_time": 0.020990473000000003,
        "avg_time_points": 1.9076086956521738,
        "cost": 3085,
        "delay_cost_type": "Continuous",
        "iterations": 78,
        "lb": 3085,
        "max_time_points": 8,
        "num_conflicts": 34,
        "num_time_points": 1053,
        "num_traveltime": 425,
        "objective_iters": 78,
        "resource_iters": 1,
        "sol_time": 54.917021,
        "solver_name": "SatDddSclTotalizer",
        "solver_time": 0.03175764,
        "status": "ok",
        "total_time": 0.052747302,
        "travel_and_resource_iters": 23,
        "travel_iters": 43,
        "ub": 3085
      }
    ],
    "trains": 14
  },
  {
    "avg_tracks": 19.25,
    "conflicting_visit_pairs": 876,
    "conflicts": 33,
    "delay_cost_type": "Continuous",
    "index": 7,
    "name": "origA5",
    "solves": [
      {
        "algorithm_time": 0.024340341,
        "avg_time_points": 2.1856540084388185,
        "cost": 3470,
        "delay_cost_type": "Continuous",
        "iterations": 78,
        "lb": 3470,
        "max_time_points": 11,
        "num_conflicts": 47,
        "num_time_points": 1036,
        "num_traveltime": 460,
        "objective_iters": 78,
        "resource_iters": 1,
        "sol_time": 62.443584,
        "solver_name": "SatDddSclTotalizer",
        "solver_time": 0.034952851,
        "status": "ok",
        "total_time": 0.059292172,
        "travel_and_resource_iters": 27,
        "travel_iters": 39,
        "ub": 3470
      }
    ],
    "trains": 12
  },
  {
    "avg_tracks": 18.625,
    "conflicting_visit_pairs": 307,
    "conflicts": 33,
    "delay_cost_type": "Continuous",
    "index": 8,
    "name": "origA6",
    "solves": [
      {
        "algorithm_time": 0.004244206000000001,
        "avg_time_points": 1.7581699346405228,
        "cost": 2068,
        "delay_cost_type": "Continuous",
        "iterations": 77,
        "lb": 2068,
        "max_time_points": 5,
        "num_conflicts": 10,
        "num_time_points": 538,
        "num_traveltime": 204,
        "objective_iters": 77,
        "resource_iters": 1,
        "sol_time": 10.05898,
        "solver_name": "SatDddSclTotalizer",
        "solver_time": 0.005409399,
        "status": "ok",
        "total_time": 0.009653053,
        "travel_and_resource_iters": 6,
        "travel_iters": 58,
        "ub": 2068
      }
    ],
    "trains": 8
  },
  {
    "avg_tracks": 12.625,
    "conflicting_visit_pairs": 126,
    "conflicts": 33,
    "delay_cost_type": "Continuous",
    "index": 9,
    "name": "origA7",
    "solves": [
      {
        "algorithm_time": 0.005954554000000001,
        "avg_time_points": 3.3666666666666667,
        "cost": 1918,
        "delay_cost_type": "Continuous",
        "iterations": 74,
        "lb": 1918,
        "max_time_points": 11,
        "num_conflicts": 31,
        "num_time_points": 707,
        "num_traveltime": 410,
        "objective_iters": 74,
        "resource_iters": 1,
        "sol_time": 14.672835,
        "solver_name": "SatDddSclTotalizer",
        "solver_time": 0.008190533,
        "status": "ok",
        "total_time": 0.014144395,
        "travel_and_resource_iters": 19,
        "travel_iters": 53,
        "ub": 1918
      }
    ],
    "trains": 8
  },
  {
    "avg_tracks": 19.214284896850586,
    "conflicting_visit_pairs": 4877,
    "conflicts": 33,
    "delay_cost_type": "Continuous",
    "index": 10,
    "name": "origA8",
    "solves": [
      {
        "algorithm_time": 6.323056107000001,
        "avg_time_points": 2.913949275362319,
        "cost": 29234,
        "delay_cost_type": "Continuous",
        "iterations": 68,
        "lb": 29234,
        "max_time_points": 20,
        "num_conflicts": 362,
        "num_time_points": 3217,
        "num_traveltime": 1417,
        "objective_iters": 68,
        "resource_iters": 1,
        "sol_time": 8888.121385,
        "solver_name": "SatDddSclTotalizer",
        "solver_time": 2.5128824119999997,
        "status": "ok",
        "total_time": 8.835936501,
        "travel_and_resource_iters": 53,
        "travel_iters": 0,
        "ub": 29234
      }
    ],
    "trains": 28
  },
  {
    "avg_tracks": 20.049999237060547,
    "conflicting_visit_pairs": 2616,
    "conflicts": 33,
    "delay_cost_type": "Continuous",
    "index": 11,
    "name": "origA9",
    "solves": [
      {
        "algorithm_time": 0.09033155400000001,
        "avg_time_points": 1.8467153284671534,
        "cost": 6991,
        "delay_cost_type": "Continuous",
        "iterations": 63,
        "lb": 6991,
        "max_time_points": 11,
        "num_conflicts": 70,
        "num_time_points": 1518,
        "num_traveltime": 537,
        "objective_iters": 63,
        "resource_iters": 1,
        "sol_time": 114.733938,
        "solver_name": "SatDddSclTotalizer",
        "solver_time": 0.02159617,
        "status": "ok",
        "total_time": 0.111926662,
        "travel_and_resource_iters": 28,
        "travel_iters": 22,
        "ub": 6991
      }
    ],
    "trains": 20
  },
  {
    "avg_tracks": 18.176469802856445,
    "conflicting_visit_pairs": 1632,
    "conflicts": 33,
    "delay_cost_type": "Continuous",
    "index": 12,
    "name": "origA10",
    "solves": [
      {
        "algorithm_time": 0.070934644,
        "avg_time_points": 2.2456692913385825,
        "cost": 5644,
        "delay_cost_type": "Continuous",
        "iterations": 58,
        "lb": 5644,
        "max_time_points": 10,
        "num_conflicts": 73,
        "num_time_points": 1426,
        "num_traveltime": 643,
        "objective_iters": 58,
        "resource_iters": 1,
        "sol_time": 107.111748,
        "solver_name": "SatDddSclTotalizer",
        "solver_time": 0.031992222,
        "status": "ok",
        "total_time": 0.102925946,
        "travel_and_resource_iters": 33,
        "travel_iters": 12,
        "ub": 5644
      }
    ],
    "trains": 17
  },
  {
    "avg_tracks": 19.83333396911621,
    "conflicting_visit_pairs": 6162,
    "conflicts": 33,
    "delay_cost_type": "Continuous",
    "index": 13,
    "name": "origA11",
    "solves": [
      {
        "algorithm_time": 0.7778725809999999,
        "avg_time_points": 2.1450819672131147,
        "cost": 8811,
        "delay_cost_type": "Continuous",
        "iterations": 87,
        "lb": 8811,
        "max_time_points": 15,
        "num_conflicts": 179,
        "num_time_points": 2617,
        "num_traveltime": 1026,
        "objective_iters": 87,
        "resource_iters": 1,
        "sol_time": 1016.308175,
        "solver_name": "SatDddSclTotalizer",
        "solver_time": 0.226690723,
        "status": "ok",
        "total_time": 1.004562172,
        "travel_and_resource_iters": 46,
        "travel_iters": 27,
        "ub": 8811
      }
    ],
    "trains": 30
  },
  {
    "avg_tracks": 21.714284896850586,
    "conflicting_visit_pairs": 6393,
    "conflicts": 33,
    "delay_cost_type": "Continuous",
    "index": 14,
    "name": "origA12",
    "solves": [
      {
        "algorithm_time": 1.786290917,
        "avg_time_points": 2.2435691318327975,
        "cost": 9085,
        "delay_cost_type": "Continuous",
        "iterations": 102,
        "lb": 9085,
        "max_time_points": 12,
        "num_conflicts": 150,
        "num_time_points": 2791,
        "num_traveltime": 1242,
        "objective_iters": 102,
        "resource_iters": 1,
        "sol_time": 2696.523907,
        "solver_name": "SatDddSclTotalizer",
        "solver_time": 0.889385574,
        "status": "ok",
        "total_time": 2.675674963,
        "travel_and_resource_iters": 61,
        "travel_iters": 27,
        "ub": 9085
      }
    ],
    "trains": 28
  },
  {
    "avg_tracks": 17.33333396911621,
    "conflicting_visit_pairs": 2022,
    "conflicts": 25,
    "delay_cost_type": "Continuous",
    "index": 15,
    "name": "origB1",
    "solves": [
      {
        "algorithm_time": 0.002604467,
        "avg_time_points": 1.1822429906542056,
        "cost": 1024,
        "delay_cost_type": "Continuous",
        "iterations": 57,
        "lb": 1024,
        "max_time_points": 4,
        "num_conflicts": 5,
        "num_time_points": 759,
        "num_traveltime": 103,
        "objective_iters": 57,
        "resource_iters": 1,
        "sol_time": 5.929625,
        "solver_name": "SatDddSclTotalizer",
        "solver_time": 0.003085875,
        "status": "ok",
        "total_time": 0.005689496,
        "travel_and_resource_iters": 3,
        "travel_iters": 42,
        "ub": 1024
      }
    ],
    "trains": 18
  },
  {
    "avg_tracks": 11.375,
    "conflicting_visit_pairs": 130,
    "conflicts": 25,
    "delay_cost_type": "Continuous",
    "index": 16,
    "name": "origB10",
    "solves": [
      {
        "algorithm_time": 0.016348147,
        "avg_time_points": 3.7,
        "cost": 6659,
        "delay_cost_type": "Continuous",
        "iterations": 54,
        "lb": 6659,
        "max_time_points": 16,
        "num_conflicts": 45,
        "num_time_points": 703,
        "num_traveltime": 403,
        "objective_iters": 54,
        "resource_iters": 1,
        "sol_time": 28.645307,
        "solver_name": "SatDddSclTotalizer",
        "solver_time": 0.011080756,
        "status": "ok",
        "total_time": 0.027428122,
        "travel_and_resource_iters": 25,
        "travel_iters": 16,
        "ub": 6659
      }
    ],
    "trains": 8
  },
  {
    "avg_tracks": 15.399999618530273,
    "conflicting_visit_pairs": 3202,
    "conflicts": 25,
    "delay_cost_type": "Continuous",
    "index": 17,
    "name": "origB11",
    "solves": [
      {
        "algorithm_time": 12.501444053,
        "avg_time_points": 2.5823899371069183,
        "cost": 79072,
        "delay_cost_type": "Continuous",
        "iterations": 44,
        "lb": 79072,
        "max_time_points": 26,
        "num_conflicts": 345,
        "num_time_points": 2053,
        "num_traveltime": 566,
        "objective_iters": 44,
        "resource_iters": 1,
        "sol_time": 17297.573557,
        "solver_name": "SatDddSclTotalizer",
        "solver_time": 1.328500626,
        "status": "ok",
        "total_time": 13.829943419,
        "travel_and_resource_iters": 27,
        "travel_iters": 0,
        "ub": 79072
      }
    ],
    "trains": 25
  },
  {
    "avg_tracks": 16.214284896850586,
    "conflicting_visit_pairs": 970,
    "conflicts": 25,
    "delay_cost_type": "Continuous",
    "index": 18,
    "name": "origB12",
    "solves": [
      {
        "algorithm_time": 0.0022034109999999997,
        "avg_time_points": 1.5320512820512822,
        "cost": 918,
        "delay_cost_type": "Continuous",
        "iterations": 91,
        "lb": 918,
        "max_time_points": 6,
        "num_conflicts": 18,
        "num_time_points": 717,
        "num_traveltime": 211,
        "objective_iters": 91,
        "resource_iters": 1,
        "sol_time": 7.524699,
        "solver_name": "SatDddSclTotalizer",
        "solver_time": 0.005266078,
        "status": "ok",
        "total_time": 0.007468829,
        "travel_and_resource_iters": 14,
        "travel_iters": 65,
        "ub": 918
      }
    ],
    "trains": 14
  },
  {
    "avg_tracks": 14.800000190734863,
    "conflicting_visit_pairs": 87,
    "conflicts": 25,
    "delay_cost_type": "Continuous",
    "index": 19,
    "name": "origB2",
    "solves": [
      {
        "algorithm_time": 0.00198058,
        "avg_time_points": 1.4183006535947713,
        "cost": 347,
        "delay_cost_type": "Continuous",
        "iterations": 55,
        "lb": 347,
        "max_time_points": 3,
        "num_conflicts": 2,
        "num_time_points": 217,
        "num_traveltime": 58,
        "objective_iters": 55,
        "resource_iters": 1,
        "sol_time": 5.255729,
        "solver_name": "SatDddSclTotalizer",
        "solver_time": 0.003034366,
        "status": "ok",
        "total_time": 0.005014173,
        "travel_and_resource_iters": 1,
        "travel_iters": 45,
        "ub": 347
      }
    ],
    "trains": 5
  },
  {
    "avg_tracks": 16.799999237060547,
    "conflicting_visit_pairs": 136,
    "conflicts": 20,
    "delay_cost_type": "Continuous",
    "index": 20,
    "name": "origB3",
    "solves": [
      {
        "algorithm_time": 0.002151939,
        "avg_time_points": 1.6878612716763006,
        "cost": 629,
        "delay_cost_type": "Continuous",
        "iterations": 43,
        "lb": 629,
        "max_time_points": 5,
        "num_conflicts": 8,
        "num_time_points": 292,
        "num_traveltime": 93,
        "objective_iters": 43,
        "resource_iters": 1,
        "sol_time": 4.960876,
        "solver_name": "SatDddSclTotalizer",
        "solver_time": 0.002587352,
        "status": "ok",
        "total_time": 0.004738583,
        "travel_and_resource_iters": 4,
        "travel_iters": 31,
        "ub": 629
      }
    ],
    "trains": 5
  },
  {
    "avg_tracks": 15.949999809265137,
    "conflicting_visit_pairs": 2246,
    "conflicts": 25,
    "delay_cost_type": "Continuous",
    "index": 21,
    "name": "origB4",
    "solves": [
      {
        "algorithm_time": 0.7773979150000001,
        "avg_time_points": 3.092705167173252,
        "cost": 54187,
        "delay_cost_type": "Continuous",
        "iterations": 96,
        "lb": 54187,
        "max_time_points": 29,
        "num_conflicts": 320,
        "num_time_points": 2035,
        "num_traveltime": 828,
        "objective_iters": 96,
        "resource_iters": 1,
        "sol_time": 2599.055662,
        "solver_name": "SatDddSclTotalizer",
        "solver_time": 1.755537669,
        "status": "ok",
        "total_time": 2.532934497,
        "travel_and_resource_iters": 75,
        "travel_iters": 5,
        "ub": 54187
      }
    ],
    "trains": 20
  },
  {
    "avg_tracks": 17.799999237060547,
    "conflicting_visit_pairs": 136,
    "conflicts": 25,
    "delay_cost_type": "Continuous",
    "index": 22,
    "name": "origB5",
    "solves": [
      {
        "algorithm_time": 0.0021387309999999996,
        "avg_time_points": 1.289617486338798,
        "cost": 288,
        "delay_cost_type": "Continuous",
        "iterations": 47,
        "lb": 288,
        "max_time_points": 3,
        "num_conflicts": 2,
        "num_time_points": 236,
        "num_traveltime": 47,
        "objective_iters": 47,
        "resource_iters": 1,
        "sol_time": 5.121514,
        "solver_name": "SatDddSclTotalizer",
        "solver_time": 0.002795489,
        "status": "ok",
        "total_time": 0.004933491,
        "travel_and_resource_iters": 1,
        "travel_iters": 37,
        "ub": 288
      }
    ],
    "trains": 5
  },
  {
    "avg_tracks": 15.199999809265137,
    "conflicting_visit_pairs": 93,
    "conflicts": 25,
    "delay_cost_type": "Continuous",
    "index": 23,
    "name": "origB6",
    "solves": [
      {
        "algorithm_time": 0.001934866,
        "avg_time_points": 1.3184713375796178,
        "cost": 176,
        "delay_cost_type": "Continuous",
        "iterations": 37,
        "lb": 176,
        "max_time_points": 3,
        "num_conflicts": 2,
        "num_time_points": 207,
        "num_traveltime": 44,
        "objective_iters": 37,
        "resource_iters": 1,
        "sol_time": 4.347468,
        "solver_name": "SatDddSclTotalizer",
        "solver_time": 0.002146066,
        "status": "ok",
        "total_time": 0.004080021,
        "travel_and_resource_iters": 1,
        "travel_iters": 35,
        "ub": 176
      }
    ],
    "trains": 5
  },
  {
    "avg_tracks": 15.25,
    "conflicting_visit_pairs": 2865,
    "conflicts": 25,
    "delay_cost_type": "Continuous",
    "index": 24,
    "name": "origB7",
    "solves": [
      {
        "algorithm_time": 7.738801364,
        "avg_time_points": 6.095238095238095,
        "cost": 68923,
        "delay_cost_type": "Continuous",
        "iterations": 156,
        "lb": 68923,
        "max_time_points": 65,
        "num_conflicts": 1435,
        "num_time_points": 4608,
        "num_traveltime": 2064,
        "objective_iters": 156,
        "resource_iters": 3,
        "sol_time": 15406.361724,
        "solver_name": "SatDddSclTotalizer",
        "solver_time": 7.485777422,
        "status": "ok",
        "total_time": 15.224577678,
        "travel_and_resource_iters": 138,
        "travel_iters": 0,
        "ub": 68923
      }
    ],
    "trains": 24
  },
  {
    "avg_tracks": 13.399999618530273,
    "conflicting_visit_pairs": 72,
    "conflicts": 25,
    "delay_cost_type": "Continuous",
    "index": 25,
    "name": "origB8",
    "solves": [
      {
        "algorithm_time": 0.002039919,
        "avg_time_points": 1.2949640287769784,
        "cost": 676,
        "delay_cost_type": "Continuous",
        "iterations": 48,
        "lb": 676,
        "max_time_points": 2,
        "num_conflicts": 1,
        "num_time_points": 180,
        "num_traveltime": 37,
        "objective_iters": 48,
        "resource_iters": 1,
        "sol_time": 5.02415,
        "solver_name": "SatDddSclTotalizer",
        "solver_time": 0.002721621,
        "status": "ok",
        "total_time": 0.004760685,
        "travel_and_resource_iters": 0,
        "travel_iters": 37,
        "ub": 676
      }
    ],
    "trains": 5
  },
  {
    "avg_tracks": 13.571428298950195,
    "conflicting_visit_pairs": 150,
    "conflicts": 25,
    "delay_cost_type": "Continuous",
    "index": 26,
    "name": "origB9",
    "solves": [
      {
        "algorithm_time": 0.026414290999999993,
        "avg_time_points": 3.568527918781726,
        "cost": 5999,
        "delay_cost_type": "Continuous",
        "iterations": 121,
        "lb": 5999,
        "max_time_points": 11,
        "num_conflicts": 32,
        "num_time_points": 703,
        "num_traveltime": 416,
        "objective_iters": 121,
        "resource_iters": 1,
        "sol_time": 79.33697,
        "solver_name": "SatDddSclTotalizer",
        "solver_time": 0.049990037,
        "status": "ok",
        "total_time": 0.076403571,
        "travel_and_resource_iters": 21,
        "travel_iters": 87,
        "ub": 5999
      }
    ],
    "trains": 7
  },
  {
    "avg_tracks": 11.375,
    "conflicting_visit_pairs": 130,
    "conflicts": 25,
    "delay_cost_type": "Continuous",
    "index": 27,
    "name": "origB10",
    "solves": [
      {
        "algorithm_time": 0.090487776,
        "avg_time_points": 4.7,
        "cost": 7805,
        "delay_cost_type": "Continuous",
        "iterations": 59,
        "lb": 7805,
        "max_time_points": 13,
        "num_conflicts": 103,
        "num_time_points": 893,
        "num_traveltime": 519,
        "objective_iters": 59,
        "resource_iters": 1,
        "sol_time": 215.737532,
        "solver_name": "SatDddSclTotalizer",
        "solver_time": 0.115546829,
        "status": "ok",
        "total_time": 0.206033701,
        "travel_and_resource_iters": 39,
        "travel_iters": 7,
        "ub": 7805
      }
    ],
    "trains": 8
  },
  {
    "avg_tracks": 15.399999618530273,
    "conflicting_visit_pairs": 3202,
    "conflicts": 25,
    "delay_cost_type": "Continuous",
    "index": 28,
    "name": "origB11",
    "solves": [
      {
        "algorithm_time": 12.085855684,
        "avg_time_points": 2.7232704402515724,
        "cost": 76944,
        "delay_cost_type": "Continuous",
        "iterations": 52,
        "lb": 76944,
        "max_time_points": 34,
        "num_conflicts": 366,
        "num_time_points": 2165,
        "num_traveltime": 651,
        "objective_iters": 52,
        "resource_iters": 1,
        "sol_time": 16193.853843,
        "solver_name": "SatDddSclTotalizer",
        "solver_time": 0.771571624,
        "status": "ok",
        "total_time": 12.857426412,
        "travel_and_resource_iters": 35,
        "travel_iters": 0,
        "ub": 76944
      }
    ],
    "trains": 25
  },
  {
    "avg_tracks": 16.214284896850586,
    "conflicting_visit_pairs": 970,
    "conflicts": 25,
    "delay_cost_type": "Continuous",
    "index": 29,
    "name": "origB12",
    "solves": [
      {
        "algorithm_time": 0.003818920000000001,
        "avg_time_points": 1.5534188034188035,
        "cost": 918,
        "delay_cost_type": "Continuous",
        "iterations": 97,
        "lb": 918,
        "max_time_points": 7,
        "num_conflicts": 18,
        "num_time_points": 727,
        "num_traveltime": 217,
        "objective_iters": 97,
        "resource_iters": 1,
        "sol_time": 10.685521,
        "solver_name": "SatDddSclTotalizer",
        "solver_time": 0.006632712,
        "status": "ok",
        "total_time": 0.010450913,
        "travel_and_resource_iters": 12,
        "travel_iters": 73,
        "ub": 918
      }
    ],
    "trains": 14
  },
  {
    "index": 30,
    "name": "trackA1",
    "trains": null,
    "conflicts": null,
    "avg_tracks": null,
    "conflicting_visit_pairs": null,
    "delay_cost_type": "cont",
    "solves": [
      {
        "solver_name": "sat_ddd_scl_totalizer",
        "status": "external_timeout",
        "external_status": "external_timeout",
        "exit_code": 124,
        "sol_time": 143534,
        "total_time": 143.534
      }
    ]
  },
  {
    "avg_tracks": 19.0,
    "conflicting_visit_pairs": 3735,
    "conflicts": 33,
    "delay_cost_type": "Continuous",
    "index": 31,
    "name": "trackA2",
    "solves": [
      {
        "algorithm_time": 1.693172146000009,
        "avg_time_points": 7.696410256410257,
        "delay_cost_type": "Continuous",
        "iterations": 114,
        "lb": 11296,
        "max_time_points": 47,
        "num_conflicts": 1113,
        "num_time_points": 7504,
        "num_traveltime": 4557,
        "objective_iters": 113,
        "resource_iters": 1,
        "sol_time": 122571.02957099999,
        "solver_name": "SatDddSclTotalizer",
        "solver_time": 120.877858353,
        "status": "timeout",
        "total_time": 122.571029571,
        "travel_and_resource_iters": 108,
        "travel_iters": 0,
        "ub": 11680
      }
    ],
    "trains": 25
  },
  {
    "avg_tracks": 22.375,
    "conflicting_visit_pairs": 2061,
    "conflicts": 33,
    "delay_cost_type": "Continuous",
    "index": 32,
    "name": "trackA3",
    "solves": [
      {
        "algorithm_time": 0.2624862299999995,
        "avg_time_points": 5.069672131147541,
        "cost": 4428,
        "delay_cost_type": "Continuous",
        "iterations": 113,
        "lb": 4428,
        "max_time_points": 23,
        "num_conflicts": 306,
        "num_time_points": 3711,
        "num_traveltime": 2357,
        "objective_iters": 113,
        "resource_iters": 1,
        "sol_time": 9637.394917,
        "solver_name": "SatDddSclTotalizer",
        "solver_time": 6.205781024,
        "status": "ok",
        "total_time": 6.468266159,
        "travel_and_resource_iters": 91,
        "travel_iters": 11,
        "ub": 4428
      }
    ],
    "trains": 16
  },
  {
    "avg_tracks": 19.214284896850586,
    "conflicting_visit_pairs": 1175,
    "conflicts": 33,
    "delay_cost_type": "Continuous",
    "index": 33,
    "name": "trackA4",
    "solves": [
      {
        "algorithm_time": 0.04814203,
        "avg_time_points": 3.597826086956522,
        "cost": 3069,
        "delay_cost_type": "Continuous",
        "iterations": 112,
        "lb": 3069,
        "max_time_points": 15,
        "num_conflicts": 115,
        "num_time_points": 1986,
        "num_traveltime": 1167,
        "objective_iters": 112,
        "resource_iters": 1,
        "sol_time": 280.924289,
        "solver_name": "SatDddSclTotalizer",
        "solver_time": 0.226646642,
        "status": "ok",
        "total_time": 0.274787323,
        "travel_and_resource_iters": 48,
        "travel_iters": 62,
        "ub": 3069
      }
    ],
    "trains": 14
  },
  {
    "avg_tracks": 19.25,
    "conflicting_visit_pairs": 876,
    "conflicts": 33,
    "delay_cost_type": "Continuous",
    "index": 34,
    "name": "trackA5",
    "solves": [
      {
        "algorithm_time": 0.06320847700000001,
        "avg_time_points": 3.1434599156118144,
        "cost": 3372,
        "delay_cost_type": "Continuous",
        "iterations": 94,
        "lb": 3372,
        "max_time_points": 21,
        "num_conflicts": 153,
        "num_time_points": 1490,
        "num_traveltime": 741,
        "objective_iters": 94,
        "resource_iters": 1,
        "sol_time": 281.631956,
        "solver_name": "SatDddSclTotalizer",
        "solver_time": 0.211122742,
        "status": "ok",
        "total_time": 0.274330295,
        "travel_and_resource_iters": 62,
        "travel_iters": 21,
        "ub": 3372
      }
    ],
    "trains": 12
  },
  {
    "avg_tracks": 18.625,
    "conflicting_visit_pairs": 307,
    "conflicts": 33,
    "delay_cost_type": "Continuous",
    "index": 35,
    "name": "trackA6",
    "solves": [
      {
        "algorithm_time": 0.00830085,
        "avg_time_points": 2.418300653594771,
        "cost": 1963,
        "delay_cost_type": "Continuous",
        "iterations": 72,
        "lb": 1963,
        "max_time_points": 8,
        "num_conflicts": 28,
        "num_time_points": 740,
        "num_traveltime": 362,
        "objective_iters": 72,
        "resource_iters": 1,
        "sol_time": 20.290381,
        "solver_name": "SatDddSclTotalizer",
        "solver_time": 0.011179441,
        "status": "ok",
        "total_time": 0.019479558,
        "travel_and_resource_iters": 19,
        "travel_iters": 51,
        "ub": 1963
      }
    ],
    "trains": 8
  },
  {
    "avg_tracks": 12.625,
    "conflicting_visit_pairs": 126,
    "conflicts": 33,
    "delay_cost_type": "Continuous",
    "index": 36,
    "name": "trackA7",
    "solves": [
      {
        "algorithm_time": 0.004549190999999999,
        "avg_time_points": 2.7285714285714286,
        "cost": 1393,
        "delay_cost_type": "Continuous",
        "iterations": 69,
        "lb": 1393,
        "max_time_points": 8,
        "num_conflicts": 28,
        "num_time_points": 573,
        "num_traveltime": 294,
        "objective_iters": 69,
        "resource_iters": 1,
        "sol_time": 11.295113,
        "solver_name": "SatDddSclTotalizer",
        "solver_time": 0.006325525,
        "status": "ok",
        "total_time": 0.010874114,
        "travel_and_resource_iters": 17,
        "travel_iters": 42,
        "ub": 1393
      }
    ],
    "trains": 8
  },
  {
    "index": 37,
    "name": "trackA8",
    "trains": null,
    "conflicts": null,
    "avg_tracks": null,
    "conflicting_visit_pairs": null,
    "delay_cost_type": "cont",
    "solves": [
      {
        "solver_name": "sat_ddd_scl_totalizer",
        "status": "external_timeout",
        "external_status": "external_timeout",
        "exit_code": 124,
        "sol_time": 143264,
        "total_time": 143.264
      }
    ]
  },
  {
    "avg_tracks": 20.049999237060547,
    "conflicting_visit_pairs": 2616,
    "conflicts": 33,
    "delay_cost_type": "Continuous",
    "index": 38,
    "name": "trackA9",
    "solves": [
      {
        "algorithm_time": 2.393029175999999,
        "avg_time_points": 6.386861313868613,
        "cost": 10465,
        "delay_cost_type": "Continuous",
        "iterations": 88,
        "lb": 10465,
        "max_time_points": 31,
        "num_conflicts": 668,
        "num_time_points": 5250,
        "num_traveltime": 3135,
        "objective_iters": 88,
        "resource_iters": 1,
        "sol_time": 77471.144704,
        "solver_name": "SatDddSclTotalizer",
        "solver_time": 68.229564329,
        "status": "ok",
        "total_time": 70.622591633,
        "travel_and_resource_iters": 74,
        "travel_iters": 0,
        "ub": 10465
      }
    ],
    "trains": 20
  },
  {
    "avg_tracks": 18.176469802856445,
    "conflicting_visit_pairs": 1632,
    "conflicts": 33,
    "delay_cost_type": "Continuous",
    "index": 39,
    "name": "trackA10",
    "solves": [
      {
        "algorithm_time": 0.438994968,
        "avg_time_points": 2.674015748031496,
        "cost": 8206,
        "delay_cost_type": "Continuous",
        "iterations": 72,
        "lb": 8206,
        "max_time_points": 13,
        "num_conflicts": 149,
        "num_time_points": 1698,
        "num_traveltime": 775,
        "objective_iters": 72,
        "resource_iters": 1,
        "sol_time": 937.831604,
        "solver_name": "SatDddSclTotalizer",
        "solver_time": 0.47225104,
        "status": "ok",
        "total_time": 0.91124517,
        "travel_and_resource_iters": 54,
        "travel_iters": 4,
        "ub": 8206
      }
    ],
    "trains": 17
  },
  {
    "index": 40,
    "name": "trackA11",
    "trains": null,
    "conflicts": null,
    "avg_tracks": null,
    "conflicting_visit_pairs": null,
    "delay_cost_type": "cont",
    "solves": [
      {
        "solver_name": "sat_ddd_scl_totalizer",
        "status": "panic",
        "external_status": "panic",
        "exit_code": 101,
        "sol_time": 52291,
        "total_time": 52.291
      }
    ]
  },
  {
    "index": 41,
    "name": "trackA12",
    "trains": null,
    "conflicts": null,
    "avg_tracks": null,
    "conflicting_visit_pairs": null,
    "delay_cost_type": "cont",
    "solves": [
      {
        "solver_name": "sat_ddd_scl_totalizer",
        "status": "external_timeout",
        "external_status": "external_timeout",
        "exit_code": 124,
        "sol_time": 144038,
        "total_time": 144.038
      }
    ]
  },
  {
    "avg_tracks": 17.33333396911621,
    "conflicting_visit_pairs": 2022,
    "conflicts": 25,
    "delay_cost_type": "Continuous",
    "index": 42,
    "name": "trackB1",
    "solves": [
      {
        "algorithm_time": 0.05125604600000001,
        "avg_time_points": 2.6791277258566977,
        "cost": 5361,
        "delay_cost_type": "Continuous",
        "iterations": 72,
        "lb": 5361,
        "max_time_points": 8,
        "num_conflicts": 108,
        "num_time_points": 1720,
        "num_traveltime": 842,
        "objective_iters": 72,
        "resource_iters": 1,
        "sol_time": 139.003526,
        "solver_name": "SatDddSclTotalizer",
        "solver_time": 0.081804225,
        "status": "ok",
        "total_time": 0.133059332,
        "travel_and_resource_iters": 45,
        "travel_iters": 15,
        "ub": 5361
      }
    ],
    "trains": 18
  },
  {
    "avg_tracks": 12.857142448425293,
    "conflicting_visit_pairs": 126,
    "conflicts": 25,
    "delay_cost_type": "Continuous",
    "index": 43,
    "name": "trackB10",
    "solves": [
      {
        "algorithm_time": 0.0022284690000000003,
        "avg_time_points": 1.4705882352941178,
        "cost": 6912,
        "delay_cost_type": "Continuous",
        "iterations": 29,
        "lb": 6912,
        "max_time_points": 4,
        "num_conflicts": 10,
        "num_time_points": 275,
        "num_traveltime": 56,
        "objective_iters": 29,
        "resource_iters": 1,
        "sol_time": 4.308564,
        "solver_name": "SatDddSclTotalizer",
        "solver_time": 0.001923032,
        "status": "ok",
        "total_time": 0.004150954,
        "travel_and_resource_iters": 5,
        "travel_iters": 11,
        "ub": 6912
      }
    ],
    "trains": 7
  },
  {
    "avg_tracks": 15.399999618530273,
    "conflicting_visit_pairs": 3202,
    "conflicts": 25,
    "delay_cost_type": "Continuous",
    "index": 44,
    "name": "trackB11",
    "solves": [
      {
        "algorithm_time": 5.610970099,
        "avg_time_points": 3.7371069182389935,
        "cost": 75445,
        "delay_cost_type": "Continuous",
        "iterations": 58,
        "lb": 75445,
        "max_time_points": 19,
        "num_conflicts": 321,
        "num_time_points": 2971,
        "num_traveltime": 1496,
        "objective_iters": 58,
        "resource_iters": 1,
        "sol_time": 14402.032309,
        "solver_name": "SatDddSclTotalizer",
        "solver_time": 5.108021346,
        "status": "ok",
        "total_time": 10.718989876,
        "travel_and_resource_iters": 42,
        "travel_iters": 0,
        "ub": 75445
      }
    ],
    "trains": 25
  },
  {
    "avg_tracks": 16.214284896850586,
    "conflicting_visit_pairs": 970,
    "conflicts": 25,
    "delay_cost_type": "Continuous",
    "index": 45,
    "name": "trackB12",
    "solves": [
      {
        "algorithm_time": 4.465660503,
        "avg_time_points": 2.128205128205128,
        "cost": 32908,
        "delay_cost_type": "Continuous",
        "iterations": 32,
        "lb": 32908,
        "max_time_points": 17,
        "num_conflicts": 83,
        "num_time_points": 996,
        "num_traveltime": 310,
        "objective_iters": 32,
        "resource_iters": 1,
        "sol_time": 4947.503149,
        "solver_name": "SatDddSclTotalizer",
        "solver_time": 0.439843758,
        "status": "ok",
        "total_time": 4.90550305,
        "travel_and_resource_iters": 15,
        "travel_iters": 1,
        "ub": 32908
      }
    ],
    "trains": 14
  },
  {
    "avg_tracks": 14.800000190734863,
    "conflicting_visit_pairs": 87,
    "conflicts": 25,
    "delay_cost_type": "Continuous",
    "index": 46,
    "name": "trackB2",
    "solves": [
      {
        "algorithm_time": 0.055831830000000006,
        "avg_time_points": 3.287581699346405,
        "cost": 11360,
        "delay_cost_type": "Continuous",
        "iterations": 47,
        "lb": 11360,
        "max_time_points": 16,
        "num_conflicts": 71,
        "num_time_points": 503,
        "num_traveltime": 224,
        "objective_iters": 47,
        "resource_iters": 1,
        "sol_time": 97.441362,
        "solver_name": "SatDddSclTotalizer",
        "solver_time": 0.035758038,
        "status": "ok",
        "total_time": 0.091588584,
        "travel_and_resource_iters": 31,
        "travel_iters": 2,
        "ub": 11360
      }
    ],
    "trains": 5
  },
  {
    "avg_tracks": 16.799999237060547,
    "conflicting_visit_pairs": 136,
    "conflicts": 20,
    "delay_cost_type": "Continuous",
    "index": 47,
    "name": "trackB3",
    "solves": [
      {
        "algorithm_time": 0.004415997,
        "avg_time_points": 3.3236994219653178,
        "cost": 861,
        "delay_cost_type": "Continuous",
        "iterations": 63,
        "lb": 861,
        "max_time_points": 9,
        "num_conflicts": 41,
        "num_time_points": 575,
        "num_traveltime": 306,
        "objective_iters": 63,
        "resource_iters": 1,
        "sol_time": 11.203068,
        "solver_name": "SatDddSclTotalizer",
        "solver_time": 0.006397741,
        "status": "ok",
        "total_time": 0.010813058,
        "travel_and_resource_iters": 22,
        "travel_iters": 32,
        "ub": 861
      }
    ],
    "trains": 5
  },
  {
    "avg_tracks": 15.949999809265137,
    "conflicting_visit_pairs": 2246,
    "conflicts": 25,
    "delay_cost_type": "Continuous",
    "index": 48,
    "name": "trackB4",
    "solves": [
      {
        "algorithm_time": 4.64855751,
        "avg_time_points": 3.685410334346505,
        "cost": 64590,
        "delay_cost_type": "Continuous",
        "iterations": 56,
        "lb": 64590,
        "max_time_points": 29,
        "num_conflicts": 307,
        "num_time_points": 2425,
        "num_traveltime": 1157,
        "objective_iters": 56,
        "resource_iters": 1,
        "sol_time": 7697.107924,
        "solver_name": "SatDddSclTotalizer",
        "solver_time": 2.853986371,
        "status": "ok",
        "total_time": 7.502542641,
        "travel_and_resource_iters": 40,
        "travel_iters": 0,
        "ub": 64590
      }
    ],
    "trains": 20
  },
  {
    "avg_tracks": 17.799999237060547,
    "conflicting_visit_pairs": 136,
    "conflicts": 25,
    "delay_cost_type": "Continuous",
    "index": 49,
    "name": "trackB5",
    "solves": [
      {
        "algorithm_time": 0.011872839999999999,
        "avg_time_points": 3.1420765027322406,
        "cost": 7474,
        "delay_cost_type": "Continuous",
        "iterations": 60,
        "lb": 7474,
        "max_time_points": 7,
        "num_conflicts": 43,
        "num_time_points": 575,
        "num_traveltime": 290,
        "objective_iters": 60,
        "resource_iters": 1,
        "sol_time": 25.425311,
        "solver_name": "SatDddSclTotalizer",
        "solver_time": 0.01265229,
        "status": "ok",
        "total_time": 0.024524432,
        "travel_and_resource_iters": 19,
        "travel_iters": 37,
        "ub": 7474
      }
    ],
    "trains": 5
  },
  {
    "avg_tracks": 15.199999809265137,
    "conflicting_visit_pairs": 93,
    "conflicts": 25,
    "delay_cost_type": "Continuous",
    "index": 50,
    "name": "trackB6",
    "solves": [
      {
        "algorithm_time": 0.0018947329999999996,
        "avg_time_points": 1.8089171974522293,
        "cost": 209,
        "delay_cost_type": "Continuous",
        "iterations": 37,
        "lb": 209,
        "max_time_points": 4,
        "num_conflicts": 6,
        "num_time_points": 284,
        "num_traveltime": 107,
        "objective_iters": 37,
        "resource_iters": 1,
        "sol_time": 4.52959,
        "solver_name": "SatDddSclTotalizer",
        "solver_time": 0.002374428,
        "status": "ok",
        "total_time": 0.004268418,
        "travel_and_resource_iters": 2,
        "travel_iters": 34,
        "ub": 209
      }
    ],
    "trains": 5
  },
  {
    "avg_tracks": 15.25,
    "conflicting_visit_pairs": 2865,
    "conflicts": 25,
    "delay_cost_type": "Continuous",
    "index": 51,
    "name": "trackB7",
    "solves": [
      {
        "algorithm_time": 19.49072263,
        "avg_time_points": 3.5343915343915344,
        "cost": 63820,
        "delay_cost_type": "Continuous",
        "iterations": 60,
        "lb": 63820,
        "max_time_points": 17,
        "num_conflicts": 306,
        "num_time_points": 2672,
        "num_traveltime": 1341,
        "objective_iters": 60,
        "resource_iters": 1,
        "sol_time": 31247.685503,
        "solver_name": "SatDddSclTotalizer",
        "solver_time": 8.03128545,
        "status": "ok",
        "total_time": 27.522007111,
        "travel_and_resource_iters": 44,
        "travel_iters": 0,
        "ub": 63820
      }
    ],
    "trains": 24
  },
  {
    "avg_tracks": 13.399999618530273,
    "conflicting_visit_pairs": 72,
    "conflicts": 25,
    "delay_cost_type": "Continuous",
    "index": 52,
    "name": "trackB8",
    "solves": [
      {
        "algorithm_time": 0.006438196,
        "avg_time_points": 2.2302158273381294,
        "cost": 7951,
        "delay_cost_type": "Continuous",
        "iterations": 54,
        "lb": 7951,
        "max_time_points": 6,
        "num_conflicts": 17,
        "num_time_points": 310,
        "num_traveltime": 131,
        "objective_iters": 54,
        "resource_iters": 1,
        "sol_time": 12.76735,
        "solver_name": "SatDddSclTotalizer",
        "solver_time": 0.005760757,
        "status": "ok",
        "total_time": 0.012198061,
        "travel_and_resource_iters": 11,
        "travel_iters": 33,
        "ub": 7951
      }
    ],
    "trains": 5
  },
  {
    "avg_tracks": 13.571428298950195,
    "conflicting_visit_pairs": 150,
    "conflicts": 25,
    "delay_cost_type": "Continuous",
    "index": 53,
    "name": "trackB9",
    "solves": [
      {
        "algorithm_time": 0.007395148999999999,
        "avg_time_points": 4.050761421319797,
        "cost": 10834,
        "delay_cost_type": "Continuous",
        "iterations": 38,
        "lb": 10834,
        "max_time_points": 20,
        "num_conflicts": 102,
        "num_time_points": 798,
        "num_traveltime": 379,
        "objective_iters": 38,
        "resource_iters": 1,
        "sol_time": 11.825336,
        "solver_name": "SatDddSclTotalizer",
        "solver_time": 0.003831696,
        "status": "ok",
        "total_time": 0.011226065,
        "travel_and_resource_iters": 27,
        "travel_iters": 0,
        "ub": 10834
      }
    ],
    "trains": 7
  },
  {
    "avg_tracks": 12.857142448425293,
    "conflicting_visit_pairs": 126,
    "conflicts": 25,
    "delay_cost_type": "Continuous",
    "index": 54,
    "name": "trackB10",
    "solves": [
      {
        "algorithm_time": 0.00875665,
        "avg_time_points": 1.588235294117647,
        "cost": 7403,
        "delay_cost_type": "Continuous",
        "iterations": 31,
        "lb": 7403,
        "max_time_points": 7,
        "num_conflicts": 16,
        "num_time_points": 297,
        "num_traveltime": 64,
        "objective_iters": 31,
        "resource_iters": 1,
        "sol_time": 12.731364,
        "solver_name": "SatDddSclTotalizer",
        "solver_time": 0.002984043,
        "status": "ok",
        "total_time": 0.01174001,
        "travel_and_resource_iters": 8,
        "travel_iters": 10,
        "ub": 7403
      }
    ],
    "trains": 7
  },
  {
    "avg_tracks": 15.399999618530273,
    "conflicting_visit_pairs": 3202,
    "conflicts": 25,
    "delay_cost_type": "Continuous",
    "index": 55,
    "name": "trackB11",
    "solves": [
      {
        "algorithm_time": 17.013848420999995,
        "avg_time_points": 4.026415094339622,
        "cost": 77669,
        "delay_cost_type": "Continuous",
        "iterations": 75,
        "lb": 77669,
        "max_time_points": 21,
        "num_conflicts": 343,
        "num_time_points": 3201,
        "num_traveltime": 1740,
        "objective_iters": 75,
        "resource_iters": 1,
        "sol_time": 45190.759539,
        "solver_name": "SatDddSclTotalizer",
        "solver_time": 24.311148196,
        "status": "ok",
        "total_time": 41.324995328,
        "travel_and_resource_iters": 57,
        "travel_iters": 1,
        "ub": 77669
      }
    ],
    "trains": 25
  },
  {
    "avg_tracks": 16.214284896850586,
    "conflicting_visit_pairs": 970,
    "conflicts": 25,
    "delay_cost_type": "Continuous",
    "index": 56,
    "name": "trackB12",
    "solves": [
      {
        "algorithm_time": 19.422744390000002,
        "avg_time_points": 2.893162393162393,
        "cost": 45352,
        "delay_cost_type": "Continuous",
        "iterations": 48,
        "lb": 45352,
        "max_time_points": 24,
        "num_conflicts": 152,
        "num_time_points": 1354,
        "num_traveltime": 554,
        "objective_iters": 48,
        "resource_iters": 1,
        "sol_time": 29214.518932,
        "solver_name": "SatDddSclTotalizer",
        "solver_time": 6.148062348,
        "status": "ok",
        "total_time": 25.570803560999998,
        "travel_and_resource_iters": 30,
        "travel_iters": 2,
        "ub": 45352
      }
    ],
    "trains": 14
  },
  {
    "index": 57,
    "name": "stationA1",
    "trains": null,
    "conflicts": null,
    "avg_tracks": null,
    "conflicting_visit_pairs": null,
    "delay_cost_type": "cont",
    "solves": [
      {
        "solver_name": "sat_ddd_scl_totalizer",
        "status": "external_timeout",
        "external_status": "external_timeout",
        "exit_code": 124,
        "sol_time": 144320,
        "total_time": 144.32
      }
    ]
  },
  {
    "index": 58,
    "name": "stationA2",
    "trains": null,
    "conflicts": null,
    "avg_tracks": null,
    "conflicting_visit_pairs": null,
    "delay_cost_type": "cont",
    "solves": [
      {
        "solver_name": "sat_ddd_scl_totalizer",
        "status": "external_timeout",
        "external_status": "external_timeout",
        "exit_code": 124,
        "sol_time": 143754,
        "total_time": 143.754
      }
    ]
  },
  {
    "avg_tracks": 22.375,
    "conflicting_visit_pairs": 2061,
    "conflicts": 33,
    "delay_cost_type": "Continuous",
    "index": 59,
    "name": "stationA3",
    "solves": [
      {
        "algorithm_time": 0.1643270939999999,
        "avg_time_points": 4.098360655737705,
        "cost": 6656,
        "delay_cost_type": "Continuous",
        "iterations": 104,
        "lb": 6656,
        "max_time_points": 16,
        "num_conflicts": 199,
        "num_time_points": 3000,
        "num_traveltime": 1828,
        "objective_iters": 104,
        "resource_iters": 1,
        "sol_time": 2242.172688,
        "solver_name": "SatDddSclTotalizer",
        "solver_time": 2.059200852,
        "status": "ok",
        "total_time": 2.223526732,
        "travel_and_resource_iters": 72,
        "travel_iters": 19,
        "ub": 6656
      }
    ],
    "trains": 16
  },
  {
    "avg_tracks": 19.214284896850586,
    "conflicting_visit_pairs": 1175,
    "conflicts": 33,
    "delay_cost_type": "Continuous",
    "index": 60,
    "name": "stationA4",
    "solves": [
      {
        "algorithm_time": 0.055265119,
        "avg_time_points": 3.6449275362318843,
        "cost": 4128,
        "delay_cost_type": "Continuous",
        "iterations": 93,
        "lb": 4128,
        "max_time_points": 17,
        "num_conflicts": 146,
        "num_time_points": 2012,
        "num_traveltime": 1175,
        "objective_iters": 93,
        "resource_iters": 1,
        "sol_time": 238.417857,
        "solver_name": "SatDddSclTotalizer",
        "solver_time": 0.17575843,
        "status": "ok",
        "total_time": 0.231022442,
        "travel_and_resource_iters": 61,
        "travel_iters": 20,
        "ub": 4128
      }
    ],
    "trains": 14
  },
  {
    "avg_tracks": 19.25,
    "conflicting_visit_pairs": 876,
    "conflicts": 33,
    "delay_cost_type": "Continuous",
    "index": 61,
    "name": "stationA5",
    "solves": [
      {
        "algorithm_time": 0.1717353800000001,
        "avg_time_points": 5.116033755274262,
        "cost": 4542,
        "delay_cost_type": "Continuous",
        "iterations": 140,
        "lb": 4542,
        "max_time_points": 31,
        "num_conflicts": 339,
        "num_time_points": 2425,
        "num_traveltime": 1466,
        "objective_iters": 140,
        "resource_iters": 1,
        "sol_time": 1243.689507,
        "solver_name": "SatDddSclTotalizer",
        "solver_time": 1.054124477,
        "status": "ok",
        "total_time": 1.225858741,
        "travel_and_resource_iters": 110,
        "travel_iters": 18,
        "ub": 4542
      }
    ],
    "trains": 12
  },
  {
    "avg_tracks": 18.625,
    "conflicting_visit_pairs": 307,
    "conflicts": 33,
    "delay_cost_type": "Continuous",
    "index": 62,
    "name": "stationA6",
    "solves": [
      {
        "algorithm_time": 0.01651865,
        "avg_time_points": 2.6143790849673203,
        "cost": 3311,
        "delay_cost_type": "Continuous",
        "iterations": 58,
        "lb": 3311,
        "max_time_points": 12,
        "num_conflicts": 53,
        "num_time_points": 800,
        "num_traveltime": 374,
        "objective_iters": 58,
        "resource_iters": 1,
        "sol_time": 32.282531,
        "solver_name": "SatDddSclTotalizer",
        "solver_time": 0.013933773,
        "status": "ok",
        "total_time": 0.030451678,
        "travel_and_resource_iters": 28,
        "travel_iters": 18,
        "ub": 3311
      }
    ],
    "trains": 8
  },
  {
    "avg_tracks": 12.625,
    "conflicting_visit_pairs": 126,
    "conflicts": 33,
    "delay_cost_type": "Continuous",
    "index": 63,
    "name": "stationA7",
    "solves": [
      {
        "algorithm_time": 0.015792316000000004,
        "avg_time_points": 2.842857142857143,
        "cost": 2200,
        "delay_cost_type": "Continuous",
        "iterations": 96,
        "lb": 2200,
        "max_time_points": 7,
        "num_conflicts": 26,
        "num_time_points": 597,
        "num_traveltime": 330,
        "objective_iters": 96,
        "resource_iters": 1,
        "sol_time": 47.302542,
        "solver_name": "SatDddSclTotalizer",
        "solver_time": 0.029812888,
        "status": "ok",
        "total_time": 0.045604353,
        "travel_and_resource_iters": 16,
        "travel_iters": 69,
        "ub": 2200
      }
    ],
    "trains": 8
  },
  {
    "avg_tracks": 19.88888931274414,
    "conflicting_visit_pairs": 4862,
    "conflicts": 33,
    "delay_cost_type": "Continuous",
    "index": 64,
    "name": "stationA8",
    "solves": [
      {
        "algorithm_time": 13.002990052000001,
        "avg_time_points": 8.082652134423252,
        "delay_cost_type": "Continuous",
        "iterations": 54,
        "lb": 22064,
        "max_time_points": 45,
        "num_conflicts": 1362,
        "num_time_points": 8899,
        "num_traveltime": 4856,
        "objective_iters": 54,
        "resource_iters": 1,
        "sol_time": 120212.73254499999,
        "solver_name": "SatDddSclTotalizer",
        "solver_time": 107.209743898,
        "status": "timeout",
        "total_time": 120.212732545,
        "travel_and_resource_iters": 52,
        "travel_iters": 0,
        "ub": 42013
      }
    ],
    "trains": 27
  },
  {
    "avg_tracks": 20.049999237060547,
    "conflicting_visit_pairs": 2616,
    "conflicts": 33,
    "delay_cost_type": "Continuous",
    "index": 65,
    "name": "stationA9",
    "solves": [
      {
        "algorithm_time": 2.615508022,
        "avg_time_points": 7.431873479318734,
        "cost": 13706,
        "delay_cost_type": "Continuous",
        "iterations": 107,
        "lb": 13706,
        "max_time_points": 38,
        "num_conflicts": 881,
        "num_time_points": 6109,
        "num_traveltime": 3693,
        "objective_iters": 107,
        "resource_iters": 1,
        "sol_time": 73917.328369,
        "solver_name": "SatDddSclTotalizer",
        "solver_time": 64.446276262,
        "status": "ok",
        "total_time": 67.061783234,
        "travel_and_resource_iters": 93,
        "travel_iters": 0,
        "ub": 13706
      }
    ],
    "trains": 20
  },
  {
    "avg_tracks": 18.176469802856445,
    "conflicting_visit_pairs": 1632,
    "conflicts": 33,
    "delay_cost_type": "Continuous",
    "index": 66,
    "name": "stationA10",
    "solves": [
      {
        "algorithm_time": 1.3165968760000002,
        "avg_time_points": 5.78740157480315,
        "cost": 9282,
        "delay_cost_type": "Continuous",
        "iterations": 151,
        "lb": 9282,
        "max_time_points": 35,
        "num_conflicts": 440,
        "num_time_points": 3675,
        "num_traveltime": 2323,
        "objective_iters": 151,
        "resource_iters": 1,
        "sol_time": 17614.070904,
        "solver_name": "SatDddSclTotalizer",
        "solver_time": 12.849444784,
        "status": "ok",
        "total_time": 14.16604021,
        "travel_and_resource_iters": 119,
        "travel_iters": 20,
        "ub": 9282
      }
    ],
    "trains": 17
  },
  {
    "index": 67,
    "name": "stationA11",
    "trains": null,
    "conflicts": null,
    "avg_tracks": null,
    "conflicting_visit_pairs": null,
    "delay_cost_type": "cont",
    "solves": [
      {
        "solver_name": "sat_ddd_scl_totalizer",
        "status": "external_timeout",
        "external_status": "external_timeout",
        "exit_code": 124,
        "sol_time": 143740,
        "total_time": 143.74
      }
    ]
  },
  {
    "index": 68,
    "name": "stationA12",
    "trains": null,
    "conflicts": null,
    "avg_tracks": null,
    "conflicting_visit_pairs": null,
    "delay_cost_type": "cont",
    "solves": [
      {
        "solver_name": "sat_ddd_scl_totalizer",
        "status": "panic",
        "external_status": "panic",
        "exit_code": 101,
        "sol_time": 49390,
        "total_time": 49.39
      }
    ]
  },
  {
    "index": 69,
    "name": "stationB1",
    "trains": null,
    "conflicts": null,
    "avg_tracks": null,
    "conflicting_visit_pairs": null,
    "delay_cost_type": "cont",
    "solves": [
      {
        "solver_name": "sat_ddd_scl_totalizer",
        "status": "external_timeout",
        "external_status": "external_timeout",
        "exit_code": 124,
        "sol_time": 143429,
        "total_time": 143.429
      }
    ]
  },
  {
    "avg_tracks": 14.800000190734863,
    "conflicting_visit_pairs": 87,
    "conflicts": 25,
    "delay_cost_type": "Continuous",
    "index": 70,
    "name": "stationB2",
    "solves": [
      {
        "algorithm_time": 0.12870715500000002,
        "avg_time_points": 3.183006535947712,
        "cost": 11174,
        "delay_cost_type": "Continuous",
        "iterations": 49,
        "lb": 11174,
        "max_time_points": 12,
        "num_conflicts": 46,
        "num_time_points": 487,
        "num_traveltime": 232,
        "objective_iters": 49,
        "resource_iters": 1,
        "sol_time": 220.249292,
        "solver_name": "SatDddSclTotalizer",
        "solver_time": 0.077562014,
        "status": "ok",
        "total_time": 0.206268249,
        "travel_and_resource_iters": 26,
        "travel_iters": 9,
        "ub": 11174
      }
    ],
    "trains": 5
  },
  {
    "avg_tracks": 16.799999237060547,
    "conflicting_visit_pairs": 136,
    "conflicts": 20,
    "delay_cost_type": "Continuous",
    "index": 71,
    "name": "stationB3",
    "solves": [
      {
        "algorithm_time": 0.004471210999999999,
        "avg_time_points": 3.6878612716763004,
        "cost": 907,
        "delay_cost_type": "Continuous",
        "iterations": 44,
        "lb": 907,
        "max_time_points": 13,
        "num_conflicts": 51,
        "num_time_points": 638,
        "num_traveltime": 349,
        "objective_iters": 44,
        "resource_iters": 1,
        "sol_time": 9.237556,
        "solver_name": "SatDddSclTotalizer",
        "solver_time": 0.00431433,
        "status": "ok",
        "total_time": 0.008784899,
        "travel_and_resource_iters": 24,
        "travel_iters": 19,
        "ub": 907
      }
    ],
    "trains": 5
  },
  {
    "avg_tracks": 15.949999809265137,
    "conflicting_visit_pairs": 2246,
    "conflicts": 25,
    "delay_cost_type": "Continuous",
    "index": 72,
    "name": "stationB4",
    "solves": [
      {
        "algorithm_time": 6.9270735210000005,
        "avg_time_points": 5.51063829787234,
        "cost": 68255,
        "delay_cost_type": "Continuous",
        "iterations": 104,
        "lb": 68255,
        "max_time_points": 34,
        "num_conflicts": 469,
        "num_time_points": 3626,
        "num_traveltime": 2134,
        "objective_iters": 104,
        "resource_iters": 1,
        "sol_time": 25105.481711,
        "solver_name": "SatDddSclTotalizer",
        "solver_time": 14.463313272,
        "status": "ok",
        "total_time": 21.390385339,
        "travel_and_resource_iters": 87,
        "travel_iters": 2,
        "ub": 68255
      }
    ],
    "trains": 20
  },
  {
    "avg_tracks": 17.799999237060547,
    "conflicting_visit_pairs": 136,
    "conflicts": 25,
    "delay_cost_type": "Continuous",
    "index": 73,
    "name": "stationB5",
    "solves": [
      {
        "algorithm_time": 0.19077529300000018,
        "avg_time_points": 5.819672131147541,
        "cost": 8006,
        "delay_cost_type": "Continuous",
        "iterations": 137,
        "lb": 8006,
        "max_time_points": 28,
        "num_conflicts": 117,
        "num_time_points": 1065,
        "num_traveltime": 688,
        "objective_iters": 137,
        "resource_iters": 1,
        "sol_time": 1352.217053,
        "solver_name": "SatDddSclTotalizer",
        "solver_time": 1.140289803,
        "status": "ok",
        "total_time": 1.331063796,
        "travel_and_resource_iters": 59,
        "travel_iters": 68,
        "ub": 8006
      }
    ],
    "trains": 5
  },
  {
    "avg_tracks": 15.199999809265137,
    "conflicting_visit_pairs": 93,
    "conflicts": 25,
    "delay_cost_type": "Continuous",
    "index": 74,
    "name": "stationB6",
    "solves": [
      {
        "algorithm_time": 0.002837605,
        "avg_time_points": 2.089171974522293,
        "cost": 461,
        "delay_cost_type": "Continuous",
        "iterations": 59,
        "lb": 461,
        "max_time_points": 4,
        "num_conflicts": 9,
        "num_time_points": 328,
        "num_traveltime": 143,
        "objective_iters": 59,
        "resource_iters": 1,
        "sol_time": 7.598621,
        "solver_name": "SatDddSclTotalizer",
        "solver_time": 0.004505626,
        "status": "ok",
        "total_time": 0.007342492,
        "travel_and_resource_iters": 5,
        "travel_iters": 43,
        "ub": 461
      }
    ],
    "trains": 5
  },
  {
    "avg_tracks": 15.25,
    "conflicting_visit_pairs": 2865,
    "conflicts": 25,
    "delay_cost_type": "Continuous",
    "index": 75,
    "name": "stationB7",
    "solves": [
      {
        "algorithm_time": 21.613190503,
        "avg_time_points": 5.199735449735449,
        "delay_cost_type": "Continuous",
        "iterations": 60,
        "lb": 66858,
        "max_time_points": 25,
        "num_conflicts": 454,
        "num_time_points": 3931,
        "num_traveltime": 2252,
        "objective_iters": 60,
        "resource_iters": 1,
        "sol_time": 120555.327391,
        "solver_name": "SatDddSclTotalizer",
        "solver_time": 98.942139792,
        "status": "timeout",
        "total_time": 120.555327391,
        "travel_and_resource_iters": 52,
        "travel_iters": 0,
        "ub": 67267
      }
    ],
    "trains": 24
  },
  {
    "avg_tracks": 13.399999618530273,
    "conflicting_visit_pairs": 72,
    "conflicts": 25,
    "delay_cost_type": "Continuous",
    "index": 76,
    "name": "stationB8",
    "solves": [
      {
        "algorithm_time": 0.0029243919999999996,
        "avg_time_points": 2.4676258992805757,
        "cost": 7966,
        "delay_cost_type": "Continuous",
        "iterations": 54,
        "lb": 7966,
        "max_time_points": 6,
        "num_conflicts": 15,
        "num_time_points": 343,
        "num_traveltime": 162,
        "objective_iters": 54,
        "resource_iters": 1,
        "sol_time": 6.904096,
        "solver_name": "SatDddSclTotalizer",
        "solver_time": 0.003693473,
        "status": "ok",
        "total_time": 0.006617196,
        "travel_and_resource_iters": 9,
        "travel_iters": 32,
        "ub": 7966
      }
    ],
    "trains": 5
  },
  {
    "avg_tracks": 13.571428298950195,
    "conflicting_visit_pairs": 150,
    "conflicts": 25,
    "delay_cost_type": "Continuous",
    "index": 77,
    "name": "stationB9",
    "solves": [
      {
        "algorithm_time": 0.036587461,
        "avg_time_points": 2.7106598984771573,
        "cost": 12006,
        "delay_cost_type": "Continuous",
        "iterations": 53,
        "lb": 12006,
        "max_time_points": 7,
        "num_conflicts": 35,
        "num_time_points": 534,
        "num_traveltime": 251,
        "objective_iters": 53,
        "resource_iters": 1,
        "sol_time": 58.849844,
        "solver_name": "SatDddSclTotalizer",
        "solver_time": 0.018787743,
        "status": "ok",
        "total_time": 0.055374184,
        "travel_and_resource_iters": 18,
        "travel_iters": 24,
        "ub": 12006
      }
    ],
    "trains": 7
  },
  {
    "avg_tracks": 12.857142448425293,
    "conflicting_visit_pairs": 126,
    "conflicts": 25,
    "delay_cost_type": "Continuous",
    "index": 78,
    "name": "stationB10",
    "solves": [
      {
        "algorithm_time": 0.00540215,
        "avg_time_points": 1.9037433155080214,
        "cost": 9166,
        "delay_cost_type": "Continuous",
        "iterations": 73,
        "lb": 9166,
        "max_time_points": 5,
        "num_conflicts": 8,
        "num_time_points": 356,
        "num_traveltime": 139,
        "objective_iters": 73,
        "resource_iters": 1,
        "sol_time": 12.200212,
        "solver_name": "SatDddSclTotalizer",
        "solver_time": 0.006350158,
        "status": "ok",
        "total_time": 0.011751633,
        "travel_and_resource_iters": 4,
        "travel_iters": 55,
        "ub": 9166
      }
    ],
    "trains": 7
  },
  {
    "index": 79,
    "name": "stationB11",
    "trains": null,
    "conflicts": null,
    "avg_tracks": null,
    "conflicting_visit_pairs": null,
    "delay_cost_type": "cont",
    "solves": [
      {
        "solver_name": "sat_ddd_scl_totalizer",
        "status": "panic",
        "external_status": "panic",
        "exit_code": 101,
        "sol_time": 128678,
        "total_time": 128.678
      }
    ]
  },
  {
    "avg_tracks": 16.214284896850586,
    "conflicting_visit_pairs": 970,
    "conflicts": 25,
    "delay_cost_type": "Continuous",
    "index": 80,
    "name": "stationB12",
    "solves": [
      {
        "algorithm_time": 15.005810667999995,
        "avg_time_points": 5.354700854700854,
        "delay_cost_type": "Continuous",
        "iterations": 72,
        "lb": 25572,
        "max_time_points": 28,
        "num_conflicts": 550,
        "num_time_points": 2506,
        "num_traveltime": 1156,
        "objective_iters": 72,
        "resource_iters": 1,
        "sol_time": 120624.17198500001,
        "solver_name": "SatDddSclTotalizer",
        "solver_time": 105.618362484,
        "status": "timeout",
        "total_time": 120.624171985,
        "travel_and_resource_iters": 57,
        "travel_iters": 0,
        "ub": 25573
      }
    ],
    "trains": 14
  }
]